pagebreaks/__init__.py
pagebreaks/_version.py
pagebreaks-0.1.13.data/data/share/jupyter/labextensions/pagebreaks/package.json
pagebreaks-0.1.13.data/data/share/jupyter/labextensions/pagebreaks/schemas/pagebreaks/package.json.orig
pagebreaks-0.1.13.data/data/share/jupyter/labextensions/pagebreaks/schemas/pagebreaks/plugin.json
pagebreaks-0.1.13.data/data/share/jupyter/labextensions/pagebreaks/static/124.9e35cf0299f2cc66b333.js
pagebreaks-0.1.13.data/data/share/jupyter/labextensions/pagebreaks/static/543.75551ad8fb9cb5c9a0cd.js
pagebreaks-0.1.13.data/data/share/jupyter/labextensions/pagebreaks/static/543.75551ad8fb9cb5c9a0cd.js.LICENSE.txt
pagebreaks-0.1.13.data/data/share/jupyter/labextensions/pagebreaks/static/728.98fb78ac9faea9dc6709.js
pagebreaks-0.1.13.data/data/share/jupyter/labextensions/pagebreaks/static/remoteEntry.31099029c586bda39143.js
pagebreaks-0.1.13.data/data/share/jupyter/labextensions/pagebreaks/static/style.js
pagebreaks-0.1.13.data/data/share/jupyter/labextensions/pagebreaks/static/third-party-licenses.json
pagebreaks-0.1.13.data/data/share/jupyter/labextensions/pagebreaks/install.json
pagebreaks-0.1.13.dist-info/METADATA
pagebreaks-0.1.13.dist-info/WHEEL
pagebreaks-0.1.13.dist-info/licenses/LICENSE
pagebreaks-0.1.13.dist-info/RECORD
