Metadata-Version: 2.3
Name: pagebreaks
Version: 0.1.13
Dynamic: Keywords
Summary: Scope Boundaries for Jupyter Notebooks
Project-URL: Homepage, https://github.com/erawn/pagebreaks
Project-URL: Bug Tracker, https://github.com/erawn/pagebreaks/issues
Project-URL: Repository, https://github.com/erawn/pagebreaks
Author-email: Eric Rawn <erawn@berkeley.edu>
License: BSD 3-Clause License
License-File: LICENSE
Classifier: Framework :: Jupyter
Classifier: Framework :: Jupyter :: JupyterLab
Classifier: Framework :: Jupyter :: JupyterLab :: 4
Classifier: Framework :: Jupyter :: JupyterLab :: Extensions
Classifier: Framework :: Jupyter :: JupyterLab :: Extensions :: Prebuilt
Classifier: License :: OSI Approved :: BSD License
Classifier: Programming Language :: Python
Classifier: Programming Language :: Python :: 3
Classifier: Programming Language :: Python :: 3.10
Classifier: Programming Language :: Python :: 3.11
Classifier: Programming Language :: Python :: 3.12
Requires-Python: >=3.10
Requires-Dist: jupyterlab>=4.0.0
Requires-Dist: pagebreaksip>=0.1.13
